onnxsim/__init__.py
onnxsim/__main__.py
onnxsim/cpp2py_export.cc
onnxsim/cxxopts.hpp
onnxsim/model_checking.py
onnxsim/model_info.py
onnxsim/onnx_simplifier.py
onnxsim/onnxsim.cpp
onnxsim/onnxsim.h
onnxsim/onnxsim_cpp2py_export.cpython-39-darwin.so
onnxsim/version.py
onnxsim/bin/onnxsim_bin.cpp
onnxsim_no_ort-0.4.0.dist-info/LICENSE
onnxsim_no_ort-0.4.0.dist-info/METADATA
onnxsim_no_ort-0.4.0.dist-info/WHEEL
onnxsim_no_ort-0.4.0.dist-info/entry_points.txt
onnxsim_no_ort-0.4.0.dist-info/top_level.txt
onnxsim_no_ort-0.4.0.dist-info/RECORD
