Metadata-Version: 2.1
Name: onnxsim-no-ort
Version: 0.4.0
Summary: Simplify your ONNX model
Home-page: https://github.com/daquexian/onnx-simplifier
Author: ONNX Simplifier Authors
Author-email: daquexian566@gmail.com
License: Apache License v2.0
Keywords: deep-learning ONNX
Classifier: Development Status :: 4 - Beta
Classifier: Intended Audience :: Developers
Classifier: License :: OSI Approved :: Apache Software License
Classifier: Programming Language :: Python :: 3 :: Only
Classifier: Programming Language :: Python :: 3.6
Classifier: Programming Language :: Python :: 3.7
Classifier: Programming Language :: Python :: 3.8
Classifier: Programming Language :: Python :: 3.9
Classifier: Programming Language :: Python :: 3.10
Classifier: Topic :: Scientific/Engineering
Classifier: Topic :: Software Development
Requires-Python: >=3.6
License-File: LICENSE
